<?xml version="1.0" encoding="UTF-8" standalone="yes"?>
<contentHaul xmlns:a="http://www.appian.com/ae/types/2009">
    <rule>
        <name>PM_dictionaryForGrid</name>
        <uuid>_a-0000db06-6d58-8000-9ba2-011c48011c48_132855</uuid>
        <description></description>
        <parentUuid>_a-0000db06-6d58-8000-9ba2-011c48011c48_132569</parentUuid>
        <visibility>
            <advertise>false</advertise>
            <hierarchy>true</hierarchy>
            <indexable>true</indexable>
            <quota>false</quota>
            <searchable>true</searchable>
            <system>false</system>
            <unlogged>false</unlogged>
        </visibility>
        <definition>={
id:ri!id,

proposalName:ri!proposalName,

requester:ri!requester,
groupId:ri!groupId,
rfType:ri!rfType,
ifOtherRf:ri!ifOtherRf,
creationDate:ri!creationDate,

rfDueDate:ri!rfDueDate,

proposalStatus:ri!proposalStatus

}</definition>
        <namedTypedValue>
            <name>id</name>
            <type>
                <name>int</name>
                <namespace>http://www.w3.org/2001/XMLSchema</namespace>
            </type>
        </namedTypedValue>
        <namedTypedValue>
            <name>proposalName</name>
            <type>
                <name>string</name>
                <namespace>http://www.w3.org/2001/XMLSchema</namespace>
            </type>
            <value/>
        </namedTypedValue>
        <namedTypedValue>
            <name>requester</name>
            <type>
                <name>string</name>
                <namespace>http://www.w3.org/2001/XMLSchema</namespace>
            </type>
            <value/>
        </namedTypedValue>
        <namedTypedValue>
            <name>groupId</name>
            <type>
                <name>int</name>
                <namespace>http://www.w3.org/2001/XMLSchema</namespace>
            </type>
        </namedTypedValue>
        <namedTypedValue>
            <name>rfType</name>
            <type>
                <name>string</name>
                <namespace>http://www.w3.org/2001/XMLSchema</namespace>
            </type>
            <value/>
        </namedTypedValue>
        <namedTypedValue>
            <name>ifOtherRf</name>
            <type>
                <name>string</name>
                <namespace>http://www.w3.org/2001/XMLSchema</namespace>
            </type>
            <value/>
        </namedTypedValue>
        <namedTypedValue>
            <name>creationDate</name>
            <type>
                <name>date</name>
                <namespace>http://www.w3.org/2001/XMLSchema</namespace>
            </type>
        </namedTypedValue>
        <namedTypedValue>
            <name>submissionDate</name>
            <type>
                <name>date</name>
                <namespace>http://www.w3.org/2001/XMLSchema</namespace>
            </type>
        </namedTypedValue>
        <namedTypedValue>
            <name>rfDueDate</name>
            <type>
                <name>date</name>
                <namespace>http://www.w3.org/2001/XMLSchema</namespace>
            </type>
        </namedTypedValue>
        <namedTypedValue>
            <name>proposalStatus</name>
            <type>
                <name>string</name>
                <namespace>http://www.w3.org/2001/XMLSchema</namespace>
            </type>
            <value/>
        </namedTypedValue>
        <preferredEditor>legacy</preferredEditor>
        <offlineEnabled>false</offlineEnabled>
    </rule>
    <roleMap public="true">
        <role allowForAll="false" inherit="true" name="readers">
            <users/>
            <groups/>
        </role>
        <role allowForAll="false" inherit="true" name="authors">
            <users/>
            <groups/>
        </role>
        <role allowForAll="false" inherit="true" name="administrators">
            <users/>
            <groups/>
        </role>
        <role allowForAll="false" inherit="false" name="denyReaders">
            <users/>
            <groups/>
        </role>
        <role allowForAll="false" inherit="false" name="denyAuthors">
            <users/>
            <groups/>
        </role>
        <role allowForAll="false" inherit="false" name="denyAdministrators">
            <users/>
            <groups/>
        </role>
    </roleMap>
    <typedValue>
        <type>
            <name>RuleTestConfig?list</name>
            <namespace>http://www.appian.com/ae/types/2009</namespace>
        </type>
        <value>
            <el>
                <a:name/>
                <a:ruleInputTestConfigs>
                    <a:value xmlns:xsi="http://www.w3.org/2001/XMLSchema-instance" xsi:nil="true"/>
                    <a:nameRef>id</a:nameRef>
                    <a:id/>
                </a:ruleInputTestConfigs>
                <a:ruleInputTestConfigs>
                    <a:value xmlns:xsi="http://www.w3.org/2001/XMLSchema-instance" xsi:nil="true"/>
                    <a:nameRef>proposalName</a:nameRef>
                    <a:id/>
                </a:ruleInputTestConfigs>
                <a:ruleInputTestConfigs>
                    <a:value xmlns:xsi="http://www.w3.org/2001/XMLSchema-instance" xsi:nil="true"/>
                    <a:nameRef>requester</a:nameRef>
                    <a:id/>
                </a:ruleInputTestConfigs>
                <a:ruleInputTestConfigs>
                    <a:value xmlns:xsi="http://www.w3.org/2001/XMLSchema-instance" xsi:nil="true"/>
                    <a:nameRef>groupId</a:nameRef>
                    <a:id/>
                </a:ruleInputTestConfigs>
                <a:ruleInputTestConfigs>
                    <a:value xmlns:xsi="http://www.w3.org/2001/XMLSchema-instance" xsi:nil="true"/>
                    <a:nameRef>rfType</a:nameRef>
                    <a:id/>
                </a:ruleInputTestConfigs>
                <a:ruleInputTestConfigs>
                    <a:value xmlns:xsi="http://www.w3.org/2001/XMLSchema-instance" xsi:nil="true"/>
                    <a:nameRef>ifOtherRf</a:nameRef>
                    <a:id/>
                </a:ruleInputTestConfigs>
                <a:ruleInputTestConfigs>
                    <a:value xmlns:xsi="http://www.w3.org/2001/XMLSchema-instance" xsi:nil="true"/>
                    <a:nameRef>creationDate</a:nameRef>
                    <a:id/>
                </a:ruleInputTestConfigs>
                <a:ruleInputTestConfigs>
                    <a:value xmlns:xsi="http://www.w3.org/2001/XMLSchema-instance" xsi:nil="true"/>
                    <a:nameRef>submissionDate</a:nameRef>
                    <a:id/>
                </a:ruleInputTestConfigs>
                <a:ruleInputTestConfigs>
                    <a:value xmlns:xsi="http://www.w3.org/2001/XMLSchema-instance" xsi:nil="true"/>
                    <a:nameRef>rfDueDate</a:nameRef>
                    <a:id/>
                </a:ruleInputTestConfigs>
                <a:ruleInputTestConfigs>
                    <a:value xmlns:xsi="http://www.w3.org/2001/XMLSchema-instance" xsi:nil="true"/>
                    <a:nameRef>proposalStatus</a:nameRef>
                    <a:id/>
                </a:ruleInputTestConfigs>
            </el>
        </value>
    </typedValue>
</contentHaul>
